[
    {
        "id": "202312291940940649",
        "title": "我国是工人阶级领导的、以工农联盟为基础的(  )的社会主义国家，国家一切权力属于人民。",
        "option": [
            "人民民主专政",
            "人民当家作主",
            "中国共产党领导",
            "民主专政"
        ],
        "answer": "A",
        "analysis": ""
    },
    {
        "id": "202312291940262923",
        "title": "( )是人民当家作主和依法治国的根本保证。",
        "option": [
            " 人民民主",
            " 党的领导",
            "宪法",
            "全过程民主"
        ],
        "answer": "B",
        "analysis": ""
    },
    {
        "id": "202312291940211889",
        "title": "人民当家作主是社会主义民主政治的本质特征，(    )是党领导人民治理国家的基本方式。",
        "option": [
            "依法治国",
            " 坚持系统观念",
            " 全过程民主",
            "民主集中制"
        ],
        "answer": "A",
        "analysis": ""
    },
    {
        "id": "202312291940466205",
        "title": "（ ）是党克敌制胜、执政兴国的重要法宝，是团结海内外全体中华儿女实现中华民族伟大复兴的重要法宝。",
        "option": [
            "协商民主",
            " 统一战线",
            "全过程人民民主",
            "实现中华民族伟大复兴"
        ],
        "answer": "B",
        "analysis": ""
    },
    {
        "id": "202312291940975313",
        "title": "（   ）是统一战线最核心、最根本的问题。",
        "option": [
            "大团结大联合",
            "广交朋友",
            "凝聚人心",
            "坚持党的领导"
        ],
        "answer": "D",
        "analysis": ""
    },
    {
        "id": "20231229194039562",
        "title": "统战工作的关键是要(   )。",
        "option": [
            "坚持求同存异",
            " 坚持党的领导",
            "坚持同一性",
            "坚持多样性"
        ],
        "answer": "A",
        "analysis": ""
    },
    {
        "id": "202312291940509382",
        "title": "社会主义民主的实质是（   ）。",
        "option": [
            "民主集中制",
            "人民当家作主",
            "人民代表大会制度",
            "中华民族大团结"
        ],
        "answer": "B",
        "analysis": ""
    },
    {
        "id": "202312291940134009",
        "title": "一个国家是不是民主，应该由这个国家的（   ）来评判，而不应该由外部少数人指手画脚来评判。",
        "option": [
            "人民",
            "执政党",
            "社会团体",
            "国家性质"
        ],
        "answer": "A",
        "analysis": ""
    },
    {
        "id": "202312291940994072",
        "title": "（  ）是社会主义的生命，没有民主就没有社会主义。",
        "option": [
            "人民民主",
            "人民当家作主",
            "以人民为中心",
            "坚持人民的主体地位"
        ],
        "answer": "A",
        "analysis": ""
    },
    {
        "id": "202312291940522255",
        "title": "（  ）是中国发展全过程人民民主的根本保证。",
        "option": [
            "人民当家作主",
            "中国特色社会主义制度",
            "人民民主专政",
            "中国共产党的领导"
        ],
        "answer": "D",
        "analysis": ""
    },
    {
        "id": "202312291940943232",
        "title": "（  ）是指民主的制度安排，实质民主是指民主始终追求的价值目标，二者有机结合。",
        "option": [
            "程序民主",
            "协商民主",
            "人民民主",
            "全过程人民民主"
        ],
        "answer": "A",
        "analysis": ""
    },
    {
        "id": "202312291940152104",
        "title": "人民民主是社会主义的生命，没有民主（  ）。",
        "option": [
            "就没有社会主义",
            "就没有社会主义的现代化",
            "就没有中华民族伟大复兴",
            "以上都对"
        ],
        "answer": "ABCD",
        "analysis": ""
    },
    {
        "id": "202312291940842609",
        "title": "（   ）构成我国的基本政治制度。",
        "option": [
            " 中国共产党领导的多党合作和政治协商制度",
            "民族区域自治制度",
            "基层群众自治制度",
            "人民代表大会制度"
        ],
        "answer": "ABC",
        "analysis": ""
    },
    {
        "id": "202312291940367371",
        "title": "中国特色社会主义政治制度（  ）。",
        "option": [
            "既把握了长期形成的历史传承，又把握了走过的发展道路",
            "把握了现实要求、着眼解决现实问题",
            "注重历史和现实、理论和实践、形式和内容有机统一",
            "具有鲜明的中国特色、民族特色、时代特色"
        ],
        "answer": "ABCD",
        "analysis": ""
    },
    {
        "id": "202312291940338805",
        "title": "中国特色社会主义政治制度的巨大优势体现在（  ）。",
        "option": [
            "能够有效保证人民享有更加广泛的权利和自由",
            "能够有效调节国家政治关系，形成安定团结的政治局面",
            "能够集中力量办大事，有效促进社会生产力解放和发展",
            "能够有效维护国家独立自主,有力维护国家主权、安全、发展利益"
        ],
        "answer": "ABCD",
        "analysis": ""
    },
    {
        "id": "20231229194099382",
        "title": "中华人民共和国的一切权力属于人民，人民行使国家权力的机关是（）。",
        "option": [
            "全国人民代表大会",
            "地方各级人民代表大会",
            "国务院",
            "人民代表"
        ],
        "answer": "AB",
        "analysis": ""
    },
    {
        "id": "202312291940298310",
        "title": "人民代表大会制度（  ）。",
        "option": [
            "坚持中国共产党领导，有效保证国家沿着社会主义道路前进",
            "最大限度保障人民当家作主",
            "有效保证国家治理跳出治乱兴衰的历史周期率",
            "正确处理事关国家前途命运的一系列重大政治关系，维护国家统一和民族团结",
            "有效保证国家政治生活既充满活力又安定有序"
        ],
        "answer": "ABCDE",
        "analysis": ""
    },
    {
        "id": "20231229194043119",
        "title": "全过程人民民主是最真实的民主,具体体现在（ ）。",
        "option": [
            "把党的主张、国家意志、人民意愿紧密融合在一起，彰显了人民民主的真实性",
            "真实反映人民的期盼、希望和诉求",
            "人民的意愿和呼声，经过民主决策程序成为党和国家的方针政策",
            "真真切切落实到国家政治生活和社会生活各方面"
        ],
        "answer": "ABCD",
        "analysis": ""
    },
    {
        "id": "202312291940604877",
        "title": "全过程人民民主是最广泛的民主,具体体现在（ ）。",
        "option": [
            "人民既充分享有民主选举权利，又充分享有民主协商、民主决策、民主管理、民主监督权利",
            "既参与国家事务管理，又参与经济和文化事业以及社会事务管理",
            "既参与国家发展顶层设计的意见建议征询，又参与地方公共事务治理",
            "不同地域、不同领域、不同层级、不同群体均实现全面覆盖"
        ],
        "answer": "ABCD",
        "analysis": ""
    },
    {
        "id": "202312291940246194",
        "title": "全过程人民民主是最管用的民主,具体体现在（ ）。",
        "option": [
            "保证在党的领导下有效治理国家，切实防止出现一盘散沙的现象",
            "保证人民依法行使权利，切实防止出现选举时漫天许诺、选举后无人过问的现象",
            "加强社会各种力量的合作协调，切实防止出现党争纷沓、相互倾轧的现象",
            "巩固平等团结互助和谐的社会主义民族关系，切实防止出现民族隔阂、民族冲突的现象",
            "发展基层民主，切实防止出现人民形式上有权、实际上无权的现象"
        ],
        "answer": "ABCDE",
        "analysis": ""
    },
    {
        "id": "202312291940244983",
        "title": "我国的协商民主体系包括（  ）。",
        "option": [
            "政党协商，人大协商",
            " 政府协商",
            " 人民团体协商",
            "政协协商",
            "基层协商以及社会组织协商"
        ],
        "answer": "ABCDE",
        "analysis": ""
    },
    {
        "id": "202312291940534816",
        "title": "我国基层民主有多种多样的形式，如(   ).。",
        "option": [
            "以村民委员会为组织形态的农村村民自治",
            "以社区居民委员会为组织形态的城市居民自治",
            "以职工代表大会为组织依托的企事业单位职工自治",
            "以上都对"
        ],
        "answer": "ABCD",
        "analysis": ""
    },
    {
        "id": "202312291940832476",
        "title": "统一战线工作的本质要求是（    ）。",
        "option": [
            "大团结大联合",
            "解决的就是人心和力量问题",
            "推进国家统一",
            "实现中华民族伟大复兴"
        ],
        "answer": "AB",
        "analysis": ""
    },
    {
        "id": "202312291940783249",
        "title": "铸牢中华民族共同体意识，就要（    ）。",
        "option": [
            "引导各族人民牢固树立休戚与共、荣辱与共、命运与共的共同体理念",
            "正确把握共同性和差异性的关系、中华民族共同体意识和各民族意识的关系、中华文化和各民族文化的关系",
            "建设各民族共有精神家园，促进各民族共同繁荣共同发展",
            "引导各族群众牢固树立正确的祖国观、民族观、文化观、历史观"
        ],
        "answer": "ABCD",
        "analysis": ""
    },
    {
        "id": "202312291940222503",
        "title": "统一战线工作范围包括（    ）。",
        "option": [
            "民主党派成员，无党派人士，党外知识分子",
            "少数民族人士，宗教界人士",
            "非公有制经济人士，新的社会阶层人士",
            "出国和归国留学人员",
            "香港同胞，澳门同胞，台湾同胞，华侨归侨及侨眷"
        ],
        "answer": "ABCDE",
        "analysis": ""
    },
    {
        "id": "202312291940123536",
        "title": "全过程人民民主是（   ）的民主，是最广泛、最真实、最管用的社会主义民主。",
        "option": [
            "全方面",
            "全链条",
            "全方位",
            "全覆盖"
        ],
        "answer": "BCD",
        "analysis": ""
    },
    {
        "id": "202312291940403224",
        "title": "全过程人民民主实现了（    ）。",
        "option": [
            " 过程民主和成果民主相统一",
            "程序民主和实质民主相统一",
            "直接民主和间接民主相统一",
            "人民民主和国家意志相统一"
        ],
        "answer": "ABCD",
        "analysis": ""
    },
    {
        "id": "202312291940152050",
        "title": " 在人民民主的共同旗帜下，中国共产党与各民主党派（   ）。",
        "option": [
            "长期共存",
            "互相监督",
            "肝胆相照",
            "荣辱与共"
        ],
        "answer": "ABCD",
        "analysis": ""
    },
    {
        "id": "202312291940251530",
        "title": "巩固和发展爱国统一战线，应该着手做好以下工作（ ）。",
        "option": [
            "坚持长期共存、互相监督、肝胆相照、荣辱与共的中国共产党领导的政治协商制度",
            "深化民族团结进步教育",
            "全面贯彻党的宗教工作基本方针",
            "牢牢把握大团结大联合的主题，做好统战工作"
        ],
        "answer": "ABCD",
        "analysis": ""
    },
    {
        "id": "202312291940379854",
        "title": "走中国特色社会主义政治发展道路，必须坚持（ ）有机统一。",
        "option": [
            "推进国家治理体系和治理能力现代化",
            "巩固和发展最广泛的爱国统一战线",
            "党的领导",
            "人民当家作主"
        ],
        "answer": "CD",
        "analysis": ""
    },
    {
        "id": "202312291940559839",
        "title": "全过程人民民主是社会主义民主政治的本质属性，是(   )的民主。",
        "option": [
            "最广泛",
            "最真实",
            "最管用",
            "最典型"
        ],
        "answer": "ABC",
        "analysis": ""
    }
]