[
    {
        "id": "202312291939479698",
        "title": " 必须坚持(   )是第一生产力。",
        "option": [
            "人才",
            "资源",
            "科技",
            "环境"
        ],
        "answer": "C",
        "analysis": ""
    },
    {
        "id": "202312291939870994",
        "title": "（ ）是发展第一动力。",
        "option": [
            "科技",
            "人才",
            "创新",
            "党的领导"
        ],
        "answer": "C",
        "analysis": ""
    },
    {
        "id": "202312291939102638",
        "title": "（ ）提出“科学技术是第一生产力”。",
        "option": [
            "毛泽东",
            "邓小平",
            "习近平",
            "胡锦涛"
        ],
        "answer": "B",
        "analysis": ""
    },
    {
        "id": "20231229193945010",
        "title": "科教兴国是我国的（  ）。",
        "option": [
            "基本国策",
            "基本政策",
            "基本路线",
            "基本战略"
        ],
        "answer": "A",
        "analysis": ""
    },
    {
        "id": "202312291939988689",
        "title": "（  ）是民族振兴、社会进步的基石。",
        "option": [
            "科技",
            "教育",
            "共同富裕",
            "人才"
        ],
        "answer": "B",
        "analysis": ""
    },
    {
        "id": "202312291939552677",
        "title": "（   ）是发展教育的根本尺度。",
        "option": [
            "科技突破",
            "人民满意",
            "实现共同富裕",
            "发展生产力"
        ],
        "answer": "B",
        "analysis": ""
    },
    {
        "id": "202312291939368017",
        "title": "（  ）是国家强盛之基、安全之要。",
        "option": [
            "科技自立自强",
            "人才引进",
            "共同富裕",
            "改革开放"
        ],
        "answer": "A",
        "analysis": ""
    },
    {
        "id": "202312291939436973",
        "title": "（  ）是我们攀登世界科技高峰的必由之路。",
        "option": [
            "自主创新",
            "脱贫攻坚",
            "守正创新",
            "信息技术"
        ],
        "answer": "A",
        "analysis": ""
    },
    {
        "id": "202312291939195853",
        "title": "必须坚持教育优先发展，把（  ）作为教育的根本任务，办好人民满意的教育。",
        "option": [
            "立德树人",
            "社会实践",
            "创新拔尖",
            "专业技术"
        ],
        "answer": "A",
        "analysis": ""
    },
    {
        "id": "202312291939494771",
        "title": "（  ）是科技创新的源头。我国面临的很多“卡脖子”技术问题，根子是基础理论研究跟不上。",
        "option": [
            "应用研究",
            "国家实验室",
            "经济特区",
            "基础研究"
        ],
        "answer": "D",
        "analysis": ""
    },
    {
        "id": "202312291939611693",
        "title": "全面建设社会主义现代化国家,(   )。",
        "option": [
            " 教育是根本",
            " 科技是关键",
            " 人才是基础",
            " 改革是保证"
        ],
        "answer": "ABC",
        "analysis": ""
    },
    {
        "id": "20231229193946515",
        "title": " 实施（  ）是增强综合国力、满足人民群众美好生活需要的必然要求，是建设教育强国、科技强国、人才强国的重大举措",
        "option": [
            " 科教兴国战略",
            " 人才强国战略",
            " 创新驱动发展战略",
            "“四个全面战略”"
        ],
        "answer": "ABC",
        "analysis": ""
    },
    {
        "id": "202312291939980936",
        "title": "实施科教兴国战略，（   ）。",
        "option": [
            "是应对新时代环境变化的必然要求",
            "是建设创新型国家的必然要求",
            "是应对国际竞争的有力举措",
            "是决胜全面小康社会的重大部署"
        ],
        "answer": "ABC",
        "analysis": ""
    },
    {
        "id": "202312291939188271",
        "title": "实施人才强国战略，（ ），实施更加积极、更加开放、更加有效的人才政策。 ",
        "option": [
            " 要坚持党管人才原则",
            " 坚持尊重劳动、尊重知识、尊重人才、尊重创造",
            " 完善人才战略布局",
            " 深化人才发展体制机制改革"
        ],
        "answer": "ABCD",
        "analysis": ""
    },
    {
        "id": "202312291939696238",
        "title": "实施创新驱动发展战略，（ ），让创新成为全社会的共同行动。",
        "option": [
            " 要坚持面向世界科技前沿、面向经济主战场",
            " 要坚持面向国家重大需求、面向人民生命健康",
            " 坚持科技创新，增强自主创新能力",
            " 坚决打赢关键核心技术攻坚战"
        ],
        "answer": "ABCD",
        "analysis": ""
    },
    {
        "id": "202312291939568209",
        "title": " 教育优先发展，要做到（ ），使我国教育越办越好。",
        "option": [
            " 经济社会发展规划优先安排教育发展",
            " 财政资金投入优先保障教育投入",
            " 公共资源配置优先满足教育和人力资源开发需要",
            " 推动健全优先发展教育事业的体制机制"
        ],
        "answer": "ABCD",
        "analysis": ""
    },
    {
        "id": "202312291939478333",
        "title": " 建设教育强国是（ ）。",
        "option": [
            " 全面建成社会主义现代化强国的战略先导",
            " 是实现高水平科技自立自强的重要支撑",
            " 是以中国式现代化全面推进中华民族伟大复兴的基础工程",
            "必须把教育事业放在优先发展的战略位置"
        ],
        "answer": "ABCD",
        "analysis": ""
    },
    {
        "id": "202312291939834218",
        "title": "必须坚持教育（ ）。 ",
        "option": [
            " 为人民服务",
            " 为中国共产党治国理政服务",
            " 为巩固和发展中国特色社会主义制度服务",
            " 为改革开放和社会主义现代化建设服务"
        ],
        "answer": "ABCD",
        "analysis": ""
    },
    {
        "id": "202312291939728172",
        "title": "落实立德树人根本任务，必须着力解决好（ ）的问题，这是教育的根本问题，也是（ ）的核心课题。",
        "option": [
            " 培养什么人",
            " 怎样培养人",
            " 为谁培养人",
            " 建设教育强国"
        ],
        "answer": "ABCD",
        "analysis": ""
    },
    {
        "id": "20231229193996212",
        "title": "我们培养的人，（ ）。",
        "option": [
            " 要坚定共产主义远大理想和中国特色社会主义共同理想",
            " 要有高尚的道德品质，厚植爱国主义情怀",
            " 要养成刻苦学习的习惯",
            " 要积极投身社会实践，增长经验和技能"
        ],
        "answer": "ABCD",
        "analysis": ""
    },
    {
        "id": "202312291939778333",
        "title": "办好人民满意的教育，（ ）。",
        "option": [
            "大力促进教育公平",
            "加快建设高质量教育体系",
            "提升教育服务经济社会发展能力",
            "坚持深化教育改革创新",
            "坚持把教师队伍建设作为基础工作"
        ],
        "answer": "ABCDE",
        "analysis": ""
    },
    {
        "id": "202312291939786727",
        "title": "实现高水平科技自立自强是（ ）。",
        "option": [
            " 应对风险挑战和维护国家利益的必然选择",
            " 构建新发展格局的内在要求",
            " 推动高质量发展的内在要求",
            " 满足人民美好生活需要的内在要求"
        ],
        "answer": "ABCD",
        "analysis": ""
    },
    {
        "id": "20231229193931330",
        "title": "建设人才强国，必须（ ）。",
        "option": [
            "走好人才自主培养之路",
            "加快建设世界重要人才中心和创新高地",
            "坚持党对人才工作的全面领导",
            "深化人才发展体制机制改革",
            "营造识才爱才敬才用才的环境",
            "BCDE"
        ],
        "answer": "ABCDE",
        "analysis": ""
    }
]